odoo10_addon_project_department-10.0.1.0.0.99.dev10-py3.8-nspkg.pth
odoo/addons/project_department/LICENSE
odoo/addons/project_department/README.rst
odoo/addons/project_department/__init__.py
odoo/addons/project_department/__manifest__.py
odoo/addons/project_department/i18n/ar.po
odoo/addons/project_department/i18n/ca.po
odoo/addons/project_department/i18n/de.po
odoo/addons/project_department/i18n/el.po
odoo/addons/project_department/i18n/es.po
odoo/addons/project_department/i18n/es_CR.po
odoo/addons/project_department/i18n/es_MX.po
odoo/addons/project_department/i18n/es_VE.po
odoo/addons/project_department/i18n/fi.po
odoo/addons/project_department/i18n/fr.po
odoo/addons/project_department/i18n/gl.po
odoo/addons/project_department/i18n/hr.po
odoo/addons/project_department/i18n/hr_HR.po
odoo/addons/project_department/i18n/hu.po
odoo/addons/project_department/i18n/it.po
odoo/addons/project_department/i18n/ja.po
odoo/addons/project_department/i18n/lt.po
odoo/addons/project_department/i18n/lv.po
odoo/addons/project_department/i18n/mk.po
odoo/addons/project_department/i18n/mn.po
odoo/addons/project_department/i18n/nl.po
odoo/addons/project_department/i18n/nl_NL.po
odoo/addons/project_department/i18n/pl.po
odoo/addons/project_department/i18n/project_department.pot
odoo/addons/project_department/i18n/pt.po
odoo/addons/project_department/i18n/pt_BR.po
odoo/addons/project_department/i18n/pt_PT.po
odoo/addons/project_department/i18n/ro.po
odoo/addons/project_department/i18n/sl.po
odoo/addons/project_department/i18n/sv.po
odoo/addons/project_department/i18n/tr.po
odoo/addons/project_department/i18n/uk.po
odoo/addons/project_department/i18n/zh_CN.po
odoo/addons/project_department/models/__init__.py
odoo/addons/project_department/models/project.py
odoo/addons/project_department/static/description/icon.png
odoo/addons/project_department/views/project.xml
odoo10_addon_project_department-10.0.1.0.0.99.dev10.dist-info/METADATA
odoo10_addon_project_department-10.0.1.0.0.99.dev10.dist-info/WHEEL
odoo10_addon_project_department-10.0.1.0.0.99.dev10.dist-info/namespace_packages.txt
odoo10_addon_project_department-10.0.1.0.0.99.dev10.dist-info/top_level.txt
odoo10_addon_project_department-10.0.1.0.0.99.dev10.dist-info/RECORD
